ckan_pilot/__init.py
ckan_pilot/root.py
ckan_pilot/commands/__init__.py
ckan_pilot/commands/catalog.py
ckan_pilot/commands/config.py
ckan_pilot/commands/dist.py
ckan_pilot/commands/extensions.py
ckan_pilot/commands/git.py
ckan_pilot/commands/init.py
ckan_pilot/commands/start.py
ckan_pilot/commands/stop.py
ckan_pilot/commands/sync.py
ckan_pilot/commands/tools.py
ckan_pilot/commands/version.py
ckan_pilot/helpers/__init__.py
ckan_pilot/helpers/catalog.py
ckan_pilot/helpers/checks.py
ckan_pilot/helpers/config.py
ckan_pilot/helpers/extensions.py
ckan_pilot/helpers/subproc.py
ckan_pilot/templates/docker.py
ckan_pilot-1.1.2.dist-info/licenses/LICENSE.md
ckan_pilot-1.1.2.dist-info/METADATA
ckan_pilot-1.1.2.dist-info/WHEEL
ckan_pilot-1.1.2.dist-info/entry_points.txt
ckan_pilot-1.1.2.dist-info/top_level.txt
ckan_pilot-1.1.2.dist-info/RECORD
