Metadata-Version: 2.4
Name: ckan-pilot
Version: 1.1.2
Summary: Manage CKAN project development, operations and maintenance with a state-of-the-art command-line interface (CLI) and modern toolset.
Author-email: Keitaro Inc <info@keitaro.com>
License-Expression: Apache-2.0
Project-URL: Homepage, https://github.com/keitaroinc/ckan-pilot
Project-URL: Issues, https://github.com/keitaroinc/ckan-pilot/issues
Requires-Python: >=3.10
License-File: LICENSE.md
Requires-Dist: auto-click-auto>=0.1.5
Requires-Dist: click>=8.1.8
Requires-Dist: click-log>=0.4.0
Requires-Dist: copier>=9.6.0
Requires-Dist: docker>=7.1.0
Requires-Dist: pyfiglet>=1.0.2
Requires-Dist: python-dotenv>=1.1.0
Requires-Dist: requests>=2.32.3
Requires-Dist: rich>=13.9.4
Dynamic: license-file
